geoexpress/__init__.py
geoexpress/async_api.py
geoexpress/batch.py
geoexpress/cli.py
geoexpress/config.py
geoexpress/exceptions.py
geoexpress/guard.py
geoexpress/logger.py
geoexpress/utils.py
geoexpress/core/__init__.py
geoexpress/core/base.py
geoexpress/core/decoder.py
geoexpress/core/encoder.py
geoexpress/core/format_detect.py
geoexpress/core/formats.py
geoexpress/core/info.py
geoexpress/core/jp2.py
geoexpress/core/metadata.py
geoexpress/core/security.py
geoexpress/core/utilities.py
geoexpress/presets/__init__.py
geoexpress/presets/compression.py
geoexpress/presets/mosaic.py
geoexpress-0.1.35.dist-info/METADATA
geoexpress-0.1.35.dist-info/WHEEL
geoexpress-0.1.35.dist-info/entry_points.txt
geoexpress-0.1.35.dist-info/top_level.txt
geoexpress-0.1.35.dist-info/RECORD
