Metadata-Version: 2.4
Name: geoexpress
Version: 0.1.35
Summary: Python SDK for LizardTech GeoExpress CLI
Author: Vibudh Bhatnagar
License-Expression: MIT
Project-URL: Homepage, https://github.com/yourusername/geoexpress
Classifier: Programming Language :: Python :: 3
Classifier: Operating System :: OS Independent
Requires-Python: >=3.8
